contour_depth/__init__.py
contour_depth/cluster.py
contour_depth/depth.py
contour_depth/synthetic_data.py
contour_depth/visualization.py
contour_depth-0.0.2.dist-info/METADATA
contour_depth-0.0.2.dist-info/WHEEL
contour_depth-0.0.2.dist-info/licenses/LICENSE
contour_depth-0.0.2.dist-info/RECORD
