Metadata-Version: 2.3
Name: contour-depth
Version: 0.0.2
Summary: Python library for computing statistical depth of ensembles of contours. The library supports the Contour Band Depth and Inclusion Depth methods. It also supports finding the ensemble's modes of variation by using depth-based clustering. Finally, it offers visualization utilities like spaghetti plots and Contour Box Plots.
Project-URL: Homepage, https://github.com/chadepl/contour-depth
Project-URL: Issues, https://github.com/chadepl/contour-depth/issues
Author-email: Nicolas Chaves-de-Plaza <n.f.chavesdeplaza@tudelft.nl>
License-File: LICENSE
Classifier: License :: OSI Approved :: MIT License
Classifier: Operating System :: OS Independent
Classifier: Programming Language :: Python :: 3
Requires-Python: >=3.4
Requires-Dist: numpy
Requires-Dist: scikit-image
Requires-Dist: scipy
